sdkboil/__init__.py
sdkboil/actions.py
sdkboil/agents.py
sdkboil/api_context.py
sdkboil/cache.py
sdkboil/callbacks.py
sdkboil/constants.py
sdkboil/deserializers.py
sdkboil/exception.py
sdkboil/headers.py
sdkboil/hooks.py
sdkboil/object.py
sdkboil/requests.py
sdkboil/serializers.py
sdkboil/utils.py
tests/__init__.py
tests/mocks.py
tests/unit.py
moveax_sdk_boilerplate-1.1.1.dist-info/METADATA
moveax_sdk_boilerplate-1.1.1.dist-info/WHEEL
moveax_sdk_boilerplate-1.1.1.dist-info/top_level.txt
moveax_sdk_boilerplate-1.1.1.dist-info/RECORD
