Metadata-Version: 2.1
Name: moveax-sdk-boilerplate
Version: 1.1.1
Summary: A simple SDK boilerplate
Home-page: https://github.com/moveaxlab/sdk-boilerplate-py
Author: MovEax
Author-email: simone.bronzini@moveax.it
License: UNKNOWN
Keywords: sdk,api,validation,boilerplate
Platform: UNKNOWN
Requires-Python: >=3
Requires-Dist: requests (==2.20.0)
Requires-Dist: moveax-validation (==1.1.2)
